tesla_powerwall/__init__.py
tesla_powerwall/api.py
tesla_powerwall/const.py
tesla_powerwall/error.py
tesla_powerwall/helpers.py
tesla_powerwall/powerwall.py
tesla_powerwall/py.typed
tesla_powerwall/responses.py
tesla_powerwall-0.3.18.dist-info/LICENSE
tesla_powerwall-0.3.18.dist-info/METADATA
tesla_powerwall-0.3.18.dist-info/WHEEL
tesla_powerwall-0.3.18.dist-info/top_level.txt
tesla_powerwall-0.3.18.dist-info/RECORD
