Metadata-Version: 2.1
Name: tesla-powerwall
Version: 0.3.18
Summary: API for Tesla Powerwall
Home-page: https://github.com/jrester/tesla_powerwall
Author: Jrester
Author-email: jrester379@gmail.com
License: UNKNOWN
Platform: UNKNOWN
Classifier: Programming Language :: Python :: 3
Classifier: License :: OSI Approved :: MIT License
License-File: LICENSE
Requires-Dist: requests (>=2.22.0)
